Workbook

Sheet DESEMPENO_UAV
A1: ANÁLISIS DE DESEMPEÑO DE PLATAFORMAS UAV
A2: Simbología | B2: Características | C2: Foam Board (Manual) | D2: Foam Board (Auto) | E2: Reno L250 (Auto) | F2: Foam Board (2200KV Variant)
A3: 1. DATOS FÍSICOS Y GEOMETRÍA (ENTRADAS CAD)
A4: b | B4: Envergadura (m) | C4: 1.05 | D4: 1.058 | E4: 1.143 | F4: 1.058
A5: S | B5: Área Alar (m²) | C5: 0.1699 | D5: 0.1699 | E5: 0.23 | F5: 0.1699
A6: L | B6: Longitud aproximada (m) | C6: 0.8 | D6: 0.81 | E6: 0.88 | F6: 0.81
A7: c | B7: Cuerda media (MAC, m) | C7: 0.155 | D7: 0.155 | E7: 0.201 | F7: 0.155
A8: AR | B8: Relación de Aspecto (Aspect Ratio) | C8: =C4^2/C5 | D8: =D4^2/D5 | E8: =E4^2/E5 | F8: =F4^2/F5
A9: 2. SISTEMA DE PROPULSIÓN Y BATERÍA (ENTRADAS ESPECIFICACIONES)
A10: - | B10: Modelo del Motor Brushless | C10: A2212 1000KV | D10: A2212 1000KV | E10: KingVal 3548 1100KV | F10: 2206 2200KV
A11: - | B11: Variador de velocidad (ESC) | C11: ESC 30A | D11: ESC 30A | E11: ESC 60A | F11: ESC 30A
A12: - | B12: Hélice seleccionada | C12: 10x4.5 | D12: 10x4.5 | E12: 12x6 | F12: 5x4.5
A13: Vbatt | B13: Voltaje nominal de batería (V) | C13: 11.1 | D13: 11.1 | E13: 11.1 | F13: 11.1
A14: C | B14: Capacidad de la batería (Ah) | C14: 2.2 | D14: 2.2 | E14: 2.2 | F14: 2.2
A15: E | B15: Energía total nominal (Wh) | C15: =C13*C14 | D15: =D13*D14 | E15: =E13*E14 | F15: =F13*F14
A16: Tkg | B16: Empuje máximo estático (kg) | C16: 0.885 | D16: 0.885 | E16: 2.218 | F16: 1.02
A17: I_cruise | B17: Corriente promedio en crucero (A) | C17: 10 | D17: 10 | E17: 20 | F17: 17
A18: I_max | B18: Corriente en máxima aceleración (A) | C18: 20 | D18: 20 | E18: 42 | F18: 25
A19: I_elec | B19: Consumo electrónica + servos (A) | C19: 1.1 | D19: 1.1 | E19: 4 | F19: 1.1
A20: 3. CONSTANTES OPERATIVAS Y LÍMITES
A21: g | B21: Aceleración de gravedad (g, m/s²) | C21: 9.81 | D21: 9.81 | E21: 9.81 | F21: 9.81
A22: ρ | B22: Densidad del aire (mar, ISA, kg/m³) | C22: 1.225 | D22: 1.225 | E22: 1.225 | F22: 1.225
A23: CLmax | B23: Coeficiente de Sustentación máximo | C23: 0.9 | D23: 0.9 | E23: 1.2 | F23: 0.9
A24: CL_CFD | B24: Coeficiente sustentación pérdida (CFD) | C24: 0.9 | D24: 0.9 | E24: N/A | F24: 0.9
A25: 4. ANÁLISIS DINÁMICO Y DESEMPEÑO CALCULADO
A26: m | B26: Masa total al despegue (MTOW, kg) | C26: =MATERIALES_USA!E17/1000 | D26: =MATERIALES_USA!J17/1000 | E26: =MATERIALES_USA!O17/1000 | F26: =MATERIALES_USA!T17/1000
A27: W | B27: Peso total estimado (W, N) | C27: =C26*C21 | D27: =D26*D21 | E27: =E26*E21 | F27: =F26*F21
A28: Vstall | B28: Velocidad de pérdida de diseño (m/s) | C28: =SQRT((2*C27)/(C22*C5*C23)) | D28: =SQRT((2*D27)/(D22*D5*D23)) | E28: =SQRT((2*E27)/(E22*E5*E23)) | F28: =SQRT((2*F27)/(F22*F5*F23))
A29: Vstall_k | B29: Velocidad de pérdida de diseño (km/h) | C29: =C28*3.6 | D29: =D28*3.6 | E29: =E28*3.6 | F29: =F28*3.6
A30: Vstall_CFD | B30: Velocidad de pérdida según CFD (m/s) | C30: =SQRT((2*C27)/(C22*C5*C24)) | D30: =SQRT((2*D27)/(D22*D5*D24)) | E30: N/A | F30: =SQRT((2*F27)/(F22*F5*F24))
A31: WL | B31: Carga Alar de Operación (g/dm²) | C31: =C26*10/C5 | D31: =D26*10/D5 | E31: =E26*10/E5 | F31: =F26*10/F5
A32: T/W_max | B32: Relación Empuje/Peso Máxima | C32: =C16/C26 | D32: =D16/D26 | E32: =E16/E26 | F32: =F16/F26
A33: t_th | B33: Autonomía Teórica en crucero (min) | C33: =(C14/(C17+C19))*60 | D33: =(D14/(D17+D19))*60 | E33: =(E14/(E17+E19))*60 | F33: =(F14/(F17+F19))*60
A34: t_pr | B34: Autonomía Práctica en crucero (70%, min) | C34: =C33*0.7 | D34: =D33*0.7 | E34: =E33*0.7 | F34: =F33*0.7
A35: t_th_max | B35: Autonomía Teórica al 100% Throttle (min) | C35: =(C14/(C18+C19))*60 | D35: =(D14/(D18+D19))*60 | E35: =(E14/(E18+E19))*60 | F35: =(F14/(F18+F19))*60
A36: t_pr_max | B36: Autonomía Práctica al 100% Throttle (min) | C36: =C35*0.7 | D36: =D35*0.7 | E36: =E35*0.7 | F36: =F35*0.7
A37: P_cruise | B37: Potencia requerida en crucero (W) | C37: =C13*C17 | D37: =D13*D17 | E37: =E13*E17 | F37: =F13*F17
A38: P_max | B38: Potencia máxima de propulsión (W) | C38: =C13*C18 | D38: =D13*D18 | E38: =E13*E18 | F38: =F13*F18
A39: V_cruise_rec | B39: Velocidad de crucero recomendada (m/s) | C39: =1.3*C28 | D39: =1.3*D28 | E39: =1.3*E28 | F39: =1.3*F28
A40: - | B40: Costo total importado (USD) | C40: =MATERIALES_USA!E29 | D40: =MATERIALES_USA!J29 | E40: =MATERIALES_USA!O29 | F40: =MATERIALES_USA!T29

Sheet MATERIALES_USA
A1: DESGLOSE DE COSTOS Y ANÁLISIS DE IMPORTACIÓN (FOB EE.UU.)
A2: Componente | B2: Especificaciones | C2: Manual Qty | D2: W Unit Manual (g) | E2: W Total Manual (g) | F2: P Unit Manual (USD) | G2: P Total Manual (USD) | H2: Auto Qty | I2: W Unit Auto (g) | J2: W Total Auto (g) | K2: P Unit Auto (USD) | L2: P Total Auto (USD) | M2: Reno Qty | N2: W Unit Reno (g) | O2: W Total Reno (g) | P2: P Unit Reno (USD) | Q2: P Total Reno (USD) | R2: Variant Qty | S2: W Unit Variant (g) | T2: W Total Variant (g) | U2: P Unit Variant (USD) | V2: P Total Variant (USD) | W2: Referencia Link
A3: Fuselaje / Estructura | B3: Madera balsa / Foam board según plataforma | C3: 1 | D3: 236 | E3: =C3*D3 | F3: 8 | G3: =C3*F3 | H3: 1 | I3: 166.45 | J3: =H3*I3 | K3: 8 | L3: =H3*K3 | M3: 1 | N3: 600 | O3: =M3*N3 | P3: 260 | Q3: =M3*P3 | R3: 1 | S3: 166.45 | T3: =R3*S3 | U3: 8 | V3: =R3*U3 | W3: https://www.joyplanes.com/es/joytrainer-mini/
A4: Motor Brushless | B4: A2212 1000KV / KingVal 3548 1100KV / 2206 2200KV | C4: 1 | D4: 50 | E4: =C4*D4 | F4: 12 | G4: =C4*F4 | H4: 1 | I4: 50 | J4: =H4*I4 | K4: 12 | L4: =H4*K4 | M4: 1 | N4: 172.08 | O4: =M4*N4 | P4: 40 | Q4: =M4*P4 | R4: 1 | S4: 35 | T4: =R4*S4 | U4: 18 | V4: =R4*U4 | W4: https://a.co/d/4o5VnrM
A5: Variador de Velocidad (ESC) | B5: ESC 30A (manual/auto/variant) / Flycolor 60A (Reno) | C5: 1 | D5: 30 | E5: =C5*D5 | F5: 10 | G5: =C5*F5 | H5: 1 | I5: 30 | J5: =H5*I5 | K5: 10 | L5: =H5*K5 | M5: 1 | N5: 100 | O5: =M5*N5 | P5: 35 | Q5: =M5*P5 | R5: 1 | S5: 30 | T5: =R5*S5 | U5: 10 | V5: =R5*U5 | W5: https://www.amazon.com/dp/B09PNFKH23
A6: Hélice de Diseño | B6: 10x4.5 (Foam) / 12x6 (Reno) / 5x4.5 (Variant) | C6: 1 | D6: 15 | E6: =C6*D6 | F6: 5 | G6: =C6*F6 | H6: 1 | I6: 15 | J6: =H6*I6 | K6: 5 | L6: =H6*K6 | M6: 1 | N6: 40 | O6: =M6*N6 | P6: 30 | Q6: =M6*P6 | R6: 1 | S6: 5 | T6: =R6*S6 | U6: 4 | V6: =R6*U6 | W6: https://a.co/d/cJSaEcq
A7: Batería LiPo 3S | B7: Lipo 3S 2200 mAh (11.1 V) | C7: 1 | D7: 200 | E7: =C7*D7 | F7: 20 | G7: =C7*F7 | H7: 1 | I7: 200 | J7: =H7*I7 | K7: 20 | L7: =H7*K7 | M7: 1 | N7: 200 | O7: =M7*N7 | P7: 20 | Q7: =M7*P7 | R7: 1 | S7: 200 | T7: =R7*S7 | U7: 20 | V7: =R7*U7 | W7: https://www.amazon.com/dp/B077P73SDS
A8: Servomotores | B8: 9g estándar (Foam) / MG996R metal gear (Reno) | C8: 4 | D8: 9 | E8: =C8*D8 | F8: 2.5 | G8: =C8*F8 | H8: 4 | I8: 9 | J8: =H8*I8 | K8: 2.5 | L8: =H8*K8 | M8: 3 | N8: 60 | O8: =M8*N8 | P8: 10 | Q8: =M8*P8 | R8: 4 | S8: 9 | T8: =R8*S8 | U8: 2.5 | V8: =R8*U8 | W8: https://www.amazon.com/s?k=MG996R
A9: Controlador de Vuelo | B9: Pixhawk 2.4.8 Autopilot | C9: 0 | D9: 0 | E9: =C9*D9 | F9: 0 | G9: =C9*F9 | H9: 1 | I9: 50 | J9: =H9*I9 | K9: 200 | L9: =H9*K9 | M9: 1 | N9: 50 | O9: =M9*N9 | P9: 200 | Q9: =M9*P9 | R9: 1 | S9: 50 | T9: =R9*S9 | U9: 200 | V9: =R9*U9 | W9: https://www.amazon.com/dp/B07CHQ7SZ4
A10: Módulo GPS / GNSS | B10: NEO-M8N GPS con soporte antena | C10: 0 | D10: 0 | E10: =C10*D10 | F10: 0 | G10: =C10*F10 | H10: 1 | I10: 20 | J10: =H10*I10 | K10: 40 | L10: =H10*K10 | M10: 1 | N10: 20 | O10: =M10*N10 | P10: 40 | Q10: =M10*P10 | R10: 1 | S10: 20 | T10: =R10*S10 | U10: 40 | V10: =R10*U10 | W10: https://www.aliexpress.com/item/3256802594266311.html
A11: Receptor Radiocontrol | B11: Flysky FS-iA6B / FS-iA10B (2.4 GHz) | C11: 1 | D11: 15 | E11: =C11*D11 | F11: 24 | G11: =C11*F11 | H11: 1 | I11: 15 | J11: =H11*I11 | K11: 24 | L11: =H11*K11 | M11: 1 | N11: 15 | O11: =M11*N11 | P11: 24 | Q11: =M11*P11 | R11: 1 | S11: 15 | T11: =R11*S11 | U11: 24 | V11: =R11*U11 | W11: https://www.amazon.com/dp/B0744DPPL8
A12: Transmisor Radiocontrol | B12: Flysky FS-i6X (Estación Terrena - No embarcado) | C12: 1 | D12: 0 | E12: =C12*D12 | F12: 60 | G12: =C12*F12 | H12: 1 | I12: 0 | J12: =H12*I12 | K12: 60 | L12: =H12*K12 | M12: 1 | N12: 0 | O12: =M12*N12 | P12: 60 | Q12: =M12*P12 | R12: 1 | S12: 0 | T12: =R12*S12 | U12: 60 | V12: =R12*U12 | W12: https://www.amazon.com/dp/B0744DPPL8
A13: Módulo de Alimentación (BEC) | B13: Power Module 5.3V BEC con enchufe XT60 | C13: 0 | D13: 0 | E13: =C13*D13 | F13: 0 | G13: =C13*F13 | H13: 1 | I13: 30 | J13: =H13*I13 | K13: 15 | L13: =H13*K13 | M13: 1 | N13: 30 | O13: =M13*N13 | P13: 15 | Q13: =M13*P13 | R13: 1 | S13: 30 | T13: =R13*S13 | U13: 15 | V13: =R13*U13 | W13: https://www.amazon.com/dp/B06XFW1X3K
A14: Acople impreso 3D | B14: Soporte motor impreso PLA (en Reno) | C14: 0 | D14: 0 | E14: =C14*D14 | F14: 0 | G14: =C14*F14 | H14: 0 | I14: 0 | J14: =H14*I14 | K14: 0 | L14: =H14*K14 | M14: 1 | N14: 50 | O14: =M14*N14 | P14: 0 | Q14: =M14*P14 | R14: 0 | S14: 0 | T14: =R14*S14 | U14: 0 | V14: =R14*U14 | W14: Diseño Interno CAD (PLA)
... A16: Otros (Tornillería, cables, velcro, pegamento, varillas) | B16: Elementos varios para integración física | C16: 1 | D16: 0 | E16: =C16*D16 | F16: 0 | G16: =C16*F16 | H16: 1 | I16: 31.55 | J16: =H16*I16 | K16: 0 | L16: =H16*K16 | M16: 1 | N16: 62.92 | O16: =M16*N16 | P16: 0 | Q16: =M16*P16 | R16: 1 | S16: 272.55 | T16: =R16*S16 | U16: 0 | V16: =R16*U16 | W16: Material de taller local
A17: SUBTOTALES (FOB EE.UU.) | E17: =SUM(E3:E16) | G17: =SUM(G3:G16) | J17: =SUM(J3:J16) | L17: =SUM(L3:L16) | O17: =SUM(O3:O16) | Q17: =SUM(Q3:Q16) | T17: =SUM(T3:T16) | V17: =SUM(V3:V16)
A19: ANÁLISIS DE COSTO DE IMPORTACIÓN A ECUADOR
A20: Costo por Libra Courier ($/lb) | E20: 5 | J20: 5 | O20: 5 | T20: 5
A21: Peso de Vuelo Total (lbs) | E21: =E17/453.592 | J21: =J17/453.592 | O21: =O17/453.592 | T21: =T17/453.592
A22: Costo por Flete (Costo Peso) | E22: =E21*E20 | J22: =J21*J20 | O22: =O21*O20 | T22: =T21*T20
A23: Precio FOB en EE.UU. (USD) | E23: =G17 | J23: =L17 | O23: =Q17 | T23: =V17
A24: Envío Doméstico en EE.UU. (Shipping 12%) | E24: =E23*0.12 | J24: =J23*0.12 | O24: =O23*0.12 | T24: =T23*0.12
A25: Impuesto Ventas EE.UU. (US Sales Tax 6%) | E25: =E23*0.06 | J25: =J23*0.06 | O25: =O23*0.06 | T25: =T23*0.06
A26: Arancel de Importación (Adunas 15% FOB) | E26: =E23*0.15 | J26: =J23*0.15 | O26: =O23*0.15 | T26: =T23*0.15
A27: FODINFA (5% FOB + $2.00 Fijo) | E27: =E23*0.05 + 2 | J27: =J23*0.05 + 2 | O27: =O23*0.05 + 2 | T27: =T23*0.05 + 2
A28: Tasa Fija Courier (Aduana Ecu.) | E28: 20 | J28: 20 | O28: 20 | T28: 20
A29: COSTO TOTAL IMPORTADO (USD) | E29: =SUM(E22,E23,E24,E25,E26,E27,E28) | J29: =SUM(J22,J23,J24,J25,J26,J27,J28) | O29: =SUM(O22,O23,O24,O25,O26,O27,O28) | T29: =SUM(T22,T23,T24,T25,T26,T27,T28)

Sheet AERODINAMICA_CFD
A1: CARACTERIZACIÓN AERODINÁMICA MEDIANTE CFD (SOLIDWORKS)
A2: Coeficientes longitudinales del Foam Board (crucero constante V = 15 m/s, q = 137.81 Pa, S = 0.1699 m²)
A3: Ángulo de Ataque (AoA, α) | B3: Coeficiente Sustentación (CL) | C3: Coeficiente Arrastre (CD) | D3: Coeficiente Momento (Cm @ CG) | E3: Eficiencia Aerodinámica (L/D)
A4: 0 | B4: 0.008 | C4: 0.155 | D4: 0.057 | E4: =B4/C4
A5: 5 | B5: 0.245 | C5: 0.104 | D5: 0.039 | E5: =B5/C5
A6: 10 | B6: 0.459 | C6: 0.128 | D6: 0.107 | E6: =B6/C6
A7: 15 | B7: 0.719 | C7: 0.244 | D7: 0.119 | E7: =B7/C7
A8: 20 | B8: 0.9 | C8: 0.367 | D8: 0.174 | E8: =B8/C8
A10: DERIVADAS DE ESTABILIDAD Y COMPORTAMIENTO LONGITUDINAL
A11: Pendiente de Sustentación (Linear CL_alpha) | C11: CL_alpha | D11: 2.71
A12: Gradiente de Momento de Cabeceo (Cm_alpha) | C12: Cm_alpha | D12: -0.205
A13: Margen Estático de Diseño (Static Margin, SM) | C13: SM | D13: =-B12/B11
